{
    "Axe": {
        "Col": [
            [ 0, 31 ],
            [ 16, 13 ],
            [ 13, 9 ],
            [ 18, 4 ],
            [ 31, 12 ],
            [ 22, 22 ],
            [ 18, 15 ]
        ],
        "Size": [ 32, 32 ],
        "FlipHorizontal": true,
        "Slots": [
            [ 1, 2 ],
            [ 2, 3 ]
        ],
        "Textures": [
            "Weapons/WoodAxe.png",
            "Weapons/StoneAxe.png"
        ],

        "Stats": {
            "Knockback": 25,
            "Angle": 240,
            "CountOfUse": 3,
            "Bounce": 0,
            "Pirce": 0
        }

    },
    "Sword": {
        "Col": [
            [ 0, 31 ],
            [ 5, 24 ],
            [ 2, 17 ],
            [ 7, 19 ],
            [ 26, 0 ],
            [ 31, 0 ],
            [ 31, 5 ],
            [ 12, 24 ],
            [ 14, 29 ],
            [ 7, 26 ]
        ],
        "Size": [ 32, 32 ],
        "Slots": [
            [ 1, 2 ],
            [ 2, 3 ]
        ],
        "FlipHorizontal": true,
        "Textures": [
            "Weapons/WoodSword.png",
            "Weapons/StoneSword.png"

        ],

        "Stats": {
            "Knockback": 10,
            "Angle": 180,
            "CountOfUse": 1,
            "Bounce": 0,
            "Pirce": 0
        }
    },
    "Pickaxe": {
        "Col": [
            [ 0, 31 ],
            [ 20, 9 ],
            [ 4, 3 ],
            [ 15, 0 ],
            [ 25, 5 ],
            [ 31, 17 ],
            [ 28, 27 ],
            [ 21, 12 ]
        ],
        "Size": [ 32, 32 ],
        "Slots": [
            [ 1, 2 ],
            [ 2, 3 ]
        ],
        "FlipHorizontal": true,
        "Textures": [
            "Weapons/WoodPickaxe.png",
            "Weapons/StonePickaxe.png"

        ],

        "Stats": {
            "Knockback": 2,
            "Angle": 280,
            "CountOfUse": 1,
            "Bounce": 0,
            "Pirce": 0
        }
    },
    "Bow": {
        "ShootPoint": [ 0, 0 ],
        "Size": [ 64, 64 ],
        "FlipHorizontal": false,
        "RotationPoint": [ 32, 32 ],
		"SpawnPoint": [ -16, -16 ],
		"AngleDiff": 90,
        "Textures": [
            "Weapons/WoodBow.png"
        ],
        "Slots": [
            [ 1, 2 ],
            [ 2, 3 ]
        ],
        "Stats": {
            "Knockback": 10,
            "Angle": 10,
            "CountOfUse": 10,
            "ReloadTime": 0,
            "UseTime": 1,
            "Bounce": 0,
            "Pirce": 5,
			"Speed":100,
			"Damage":1
        }

    },
    "Arrow": {
        "Col": [
            [ 19, 12 ],
            [ 19, 7 ],
            [ 29, 2 ],
            [ 24, 12 ]
        ],
        "Size": [ 32, 32 ],
        "FlipHorizontal": true,
        "RotationPoint": [ 16, 16 ],
        "Textures": [
            "Weapons/WoodArrow.png"

        ]
    }
}